rifleman/__init__.py
rifleman/__main__.py
rifleman/py.typed
rifleman-0.1.9.dist-info/LICENSE
rifleman-0.1.9.dist-info/METADATA
rifleman-0.1.9.dist-info/WHEEL
rifleman-0.1.9.dist-info/entry_points.txt
rifleman-0.1.9.dist-info/top_level.txt
rifleman-0.1.9.dist-info/RECORD
