Metadata-Version: 2.1
Name: rifleman
Version: 0.1.9
Summary: an extendible dispatcher to lint/format code, based on rifle
Home-page: https://github.com/seanbreckenridge/rifleman
Author: Sean Breckenridge
Author-email: seanbrecke@gmail.com
License: https://raw.githubusercontent.com/ranger/ranger/master/LICENSE
Keywords: lint
Classifier: License :: OSI Approved :: GNU General Public License v3 (GPLv3)
Classifier: Programming Language :: Python
Classifier: Programming Language :: Python :: 3
Classifier: Programming Language :: Python :: 3.7
Classifier: Programming Language :: Python :: 3.8
Classifier: Programming Language :: Python :: 3.9
Classifier: Programming Language :: Python :: 3.10
License-File: LICENSE
Requires-Dist: requests
Provides-Extra: testing
Requires-Dist: pytest ; extra == 'testing'
Requires-Dist: mypy ; extra == 'testing'
